yaqd_ekspla/VERSION
yaqd_ekspla/__init__.py
yaqd_ekspla/__version__.py
yaqd_ekspla/_ekspla_nt340.py
yaqd_ekspla/ekspla-nt340.avpr
yaqd_ekspla/ekspla-nt340.toml
yaqd_ekspla-2022.11.0.dist-info/entry_points.txt
yaqd_ekspla-2022.11.0.dist-info/LICENSE
yaqd_ekspla-2022.11.0.dist-info/WHEEL
yaqd_ekspla-2022.11.0.dist-info/METADATA
yaqd_ekspla-2022.11.0.dist-info/RECORD
